makemore/__init__.py
makemore/datasets.py
makemore/py.typed
makemore/utils/__init__.py
makemore/utils/const.py
makemore/utils/types.py
makemore-0.1.8.dist-info/WHEEL
makemore-0.1.8.dist-info/METADATA
makemore-0.1.8.dist-info/RECORD
