Metadata-Version: 2.1
Name: makemore
Version: 0.1.8
Summary: ♻️ Generate more of the same stuff
Author-email: Luca Baggi <57922983+baggiponte@users.noreply.github.com>
Requires-Python: >=3.9
Requires-Dist: numpy>=1.22.0
Requires-Dist: requests>=2.27.0
Requires-Dist: torch>=2.0.1
Requires-Dist: typing-extensions>=4.7.1; python_version < "3.11"
